jupyterlab_notebook_autosave/__init__.py
jupyterlab_notebook_autosave/_version.py
jupyterlab_notebook_autosave-0.2.0.data/data/share/jupyter/labextensions/jupyterlab-notebook-autosave/build_log.json
jupyterlab_notebook_autosave-0.2.0.data/data/share/jupyter/labextensions/jupyterlab-notebook-autosave/package.json
jupyterlab_notebook_autosave-0.2.0.data/data/share/jupyter/labextensions/jupyterlab-notebook-autosave/schemas/jupyterlab-notebook-autosave/package.json.orig
jupyterlab_notebook_autosave-0.2.0.data/data/share/jupyter/labextensions/jupyterlab-notebook-autosave/schemas/jupyterlab-notebook-autosave/plugin.json
jupyterlab_notebook_autosave-0.2.0.data/data/share/jupyter/labextensions/jupyterlab-notebook-autosave/static/lib_index_js.3fd1a2fd12081d98e9fb.js
jupyterlab_notebook_autosave-0.2.0.data/data/share/jupyter/labextensions/jupyterlab-notebook-autosave/static/lib_index_js.3fd1a2fd12081d98e9fb.js.map
jupyterlab_notebook_autosave-0.2.0.data/data/share/jupyter/labextensions/jupyterlab-notebook-autosave/static/node_modules_dayjs_dayjs_min_js.b8ea7dfcc434fe782134.js
jupyterlab_notebook_autosave-0.2.0.data/data/share/jupyter/labextensions/jupyterlab-notebook-autosave/static/node_modules_dayjs_dayjs_min_js.b8ea7dfcc434fe782134.js.map
jupyterlab_notebook_autosave-0.2.0.data/data/share/jupyter/labextensions/jupyterlab-notebook-autosave/static/remoteEntry.9a0869aabb81d8747957.js
jupyterlab_notebook_autosave-0.2.0.data/data/share/jupyter/labextensions/jupyterlab-notebook-autosave/static/remoteEntry.9a0869aabb81d8747957.js.map
jupyterlab_notebook_autosave-0.2.0.data/data/share/jupyter/labextensions/jupyterlab-notebook-autosave/static/style.js
jupyterlab_notebook_autosave-0.2.0.data/data/share/jupyter/labextensions/jupyterlab-notebook-autosave/static/style_index_js.625367080a734a49b48f.js
jupyterlab_notebook_autosave-0.2.0.data/data/share/jupyter/labextensions/jupyterlab-notebook-autosave/static/style_index_js.625367080a734a49b48f.js.map
jupyterlab_notebook_autosave-0.2.0.dist-info/METADATA
jupyterlab_notebook_autosave-0.2.0.dist-info/WHEEL
jupyterlab_notebook_autosave-0.2.0.dist-info/RECORD
