Metadata-Version: 2.3
Name: jupyterlab_notebook_autosave
Version: 0.2.0
Dynamic: Keywords
Summary: A JupyterLab extension that will autosave your open Notebook.
Project-URL: Homepage, https://github.com/datawars-io/jupyterlab-notebook-autosave
Project-URL: Bug Tracker, https://github.com/datawars-io/jupyterlab-notebook-autosave/issues
Project-URL: Repository, https://github.com/datawars-io/jupyterlab-notebook-autosave.git
Author-email: "datawars.io" <info@datawars.io>
Classifier: Framework :: Jupyter
Classifier: Framework :: Jupyter :: JupyterLab
Classifier: Framework :: Jupyter :: JupyterLab :: 4
Classifier: Framework :: Jupyter :: JupyterLab :: Extensions
Classifier: Framework :: Jupyter :: JupyterLab :: Extensions :: Prebuilt
Classifier: Programming Language :: Python
Classifier: Programming Language :: Python :: 3
Classifier: Programming Language :: Python :: 3.8
Classifier: Programming Language :: Python :: 3.9
Classifier: Programming Language :: Python :: 3.10
Classifier: Programming Language :: Python :: 3.11
Classifier: Programming Language :: Python :: 3.12
Requires-Python: >=3.8
